{
  "contagi": "contagio",
  "ospedali": "ospedale",
  "medici": "medico",
  "informazioni": "informazione",
  "dati": "dato",
  "disposizioni": "disposizione",
  "sanitarie": "sanitaria",
  "numeri": "numero",
  "contatti": "contatto",
  "indicazioni": "indicazione",
  "genitori": "genitore",
  "direttive": "direttiva",
  "decreti": "decreto",
  "anziani": "anziano",
  "diffondersi": "diffondere",
  "far": "fare",
  "decessi": "decesso",
  "deboli": "debole",
  "alta": "alto",
  "alte": "alto",
  "alti": "alto",
  "voglio": "volere",
  "familiari": "familiare",
  "misure": "misura",
  "amici": "amico",
  "malati": "malato",
  "malate": "malato",
  "malata": "malato",
  "comunicazioni": "comunicazione",
  "governativo": "governative",
  "appelli": "appello",
  "aziende": "azienda",
  "ammalarsi": "ammalare",
  "ministeriali": "ministeriale",
  "cucino": "cucinare",
  "cucina": "cucinare",
  "leggo": "leggere",
  "guardo": "guardare",
  "lettura": "leggere",
  "studio": "studiare",
  "gioco": "giocare",
  "lavoro": "lavorare",
  "leggendo": "leggere",
  "lavori": "lavorare",
  "pulisco": "pulire",
  "guardando": "guardare",
  "giochi": "giocare",
  "disegno": "disegnare",
  "ascolto": "ascoltare",
  "cucinando": "cucinare",
  "corsi": "corso",
  "compiti": "compito",
  "giocando": "giocare",
  "figlia": "figlio",
  "figlie": "figlio",
  "figli": "figlio",
  "occupo": "occupare",
  "sistemo": "sistemare",
  "progetti": "progetto",
  "esercizi": "esercizio",
  "dedico": "dedicare",
  "lezioni": "lezione",
  "personali": "personale",
  "domestici": "domestico",
  "domestiche": "domestico",
  "domestica": "domestico",
  "parlo": "parlare",
  "alleno": "allenare",
  "seguo": "seguire",
  "informo": "informare",
  "vedo": "vedere",
  "notizie": "notizia",
  "studiando": "studiare",
  "sento": "sentire",
  "articoli": "articolo",
  "lavorando": "lavorare",
  "dormo": "dormire",
  "aiuto": "aiutare",
  "chiamo": "ciamare",
  "curo": "curare",
  "dipingo": "dipingere",
  "lavoretti": "lavoro",
  "scrivo": "scrivere",
  "regole": "regola",
  "infermieri": "infermiere",
  "infermiera": "infermiere",
  "italiani": "italiano",
  "italiana": "italiano",
  "ricercatori": "ricercatore",
  "sanitari": "sanitario",
  "uniti": "unito",
  "possano": "potere",
  "poter": "potere",
  "ammali": "ammalare",
  "ammalino": "ammalare",
  "ammalarmi": "ammalare",
  "famigliari": "familgiare",
  "parenti": "parente",
  "economiche": "economico",
  "economici": "economico",
  "economica": "economico",
  "morti": "morte",
  "care": "cari",
  "giornate": "giornata"
}
